sjjcb-py-captcha-util/__init__.py
sjjcb-py-captcha-util/captchaAction.py
sjjcbCaptcha/__init__.py
sjjcbCaptcha/captchaAction.py
sjjcbCaptcha-1.2.1.dist-info/LICENSE
sjjcbCaptcha-1.2.1.dist-info/METADATA
sjjcbCaptcha-1.2.1.dist-info/WHEEL
sjjcbCaptcha-1.2.1.dist-info/top_level.txt
sjjcbCaptcha-1.2.1.dist-info/RECORD
