Metadata-Version: 2.1
Name: sjjcbCaptcha
Version: 1.2.1
Summary: Public POM project: sjjcbCaptcha 
Home-page: http://www.example.com
Author: zijian
Author-email: ah.fanjian@aisino.com
License: Apache License 2.0
Platform: UNKNOWN
Classifier: Programming Language :: Python :: 3
Classifier: Operating System :: OS Independent
